rapid_desktop_switcher/__init__.py
rapid_desktop_switcher/config.py
rapid_desktop_switcher-0.3.1.dist-info/METADATA
rapid_desktop_switcher-0.3.1.dist-info/WHEEL
rapid_desktop_switcher-0.3.1.dist-info/entry_points.txt
rapid_desktop_switcher-0.3.1.dist-info/top_level.txt
rapid_desktop_switcher-0.3.1.dist-info/RECORD
