Metadata-Version: 2.1
Name: rapid-desktop-switcher
Version: 0.3.1
Summary: Change your virtual desktop with the press of a key. Helpful as a panic button.
Home-page: https://example.com
Author: Bruce Blore
Author-email: bruceblore@protonmail.com
License: UNKNOWN
Platform: UNKNOWN
Classifier: Programming Language :: Python :: 3
Classifier: License :: OSI Approved :: MIT License
Classifier: Operating System :: OS Independent
